{
  "properties": [
    {
      "id": "1",
      "title": "Modern Villa with Pool in Libreville",
      "slug": "modern-villa-libreville",
      "price": 450000000,
      "priceUnit": "FCFA",
      "listingType": "buy",
      "type": "villa",
      "location": "Batterie IV, Libreville",
      "city": "Libreville",
      "country": "Gabon",
      "rooms": 5,
      "bedrooms": 5,
      "bathrooms": 4,
      "surface": 350,
      "landSize": 600,
      "description": "Magnifique villa moderne avec piscine située dans le quartier résidentiel de Batterie IV. Profitez d'un cadre luxueux avec jardin paysager, piscine à débordement et finitions haut de gamme. La villa dispose de 5 chambres spacieuses, toutes avec salle de bain privative, une cuisine américaine entièrement équipée, un grand salon donnant sur la piscine, et un garage pour 3 voitures. Idéale pour une famille ou pour des réceptions.",
      "features": ["Piscine à débordement", "Jardin paysager", "Parking 3 places", "Climatisation réversible", "Cuisine équipée", "Vidéosurveillance", "Domotique", "Groupe électrogène", "Forage"],
      "images": [
        "https://images.unsplash.com/photo-1613490493576-7fde63acd811?w=800&q=80",
        "https://images.unsplash.com/photo-1583608205776-bfd35f0d9f83?w=800&q=80",
        "https://images.unsplash.com/photo-1582268611958-ebfd161ef9cf?w=800&q=80",
        "https://images.unsplash.com/photo-1600585154340-be6161a56a0c?w=800&q=80"
      ],
      "verified": true,
      "isNew": false,
      "isUrgent": false,
      "isFeatured": true,
      "agent": {
        "id": "a1",
        "name": "Aminata Diallo",
        "agency": "Afro Homes",
        "rating": 4.7,
        "listings": 52,
        "avatar": "https://images.unsplash.com/photo-1494790108377-be9c29b29330?w=150&q=80",
        "phone": "+241 77 123 456",
        "email": "aminata@afrohomes.com"
      },
      "createdAt": "2025-01-15T10:00:00Z"
    },
    {
      "id": "2",
      "title": "Luxury Apartment in Douala City Center",
      "slug": "luxury-apartment-douala",
      "price": 75000000,
      "priceUnit": "FCFA",
      "listingType": "buy",
      "type": "apartment",
      "location": "Bonanjo, Douala",
      "city": "Douala",
      "country": "Cameroon",
      "rooms": 3,
      "bedrooms": 3,
      "bathrooms": 2,
      "surface": 120,
      "description": "Appartement de luxe en plein cœur de Douala, situé dans une résidence sécurisée. Idéal pour investisseurs ou familles recherchant confort et commodités. Proche des commerces, banques et restaurants. Vue imprenable sur la ville.",
      "features": ["Ascenseur", "Parking sécurisé", "Climatisation", "Garde 24h/24", "Groupe électrogène", "Eau courante 24h/24", "Salle de sport", "Piscine commune"],
      "images": [
        "https://images.unsplash.com/photo-1560448204-e02f11c3d0e2?w=800&q=80",
        "https://images.unsplash.com/photo-1522708323590-d24dbb6b0267?w=800&q=80",
        "https://images.unsplash.com/photo-1560185008-8c45f4e2d7b1?w=800&q=80"
      ],
      "verified": false,
      "isNew": true,
      "isUrgent": false,
      "isFeatured": true,
      "agent": {
        "id": "a2",
        "name": "Jean Mbarga",
        "agency": "Immo Douala",
        "rating": 4.5,
        "listings": 38,
        "avatar": "https://images.unsplash.com/photo-1507003211169-0a1dd7228f2d?w=150&q=80",
        "phone": "+237 6 77 88 99 00",
        "email": "jean@immodouala.com"
      },
      "createdAt": "2025-02-20T10:00:00Z"
    },
    {
      "id": "3",
      "title": "Prime Commercial Land in Yaoundé",
      "slug": "commercial-land-yaounde",
      "price": 180000000,
      "priceUnit": "FCFA",
      "listingType": "buy",
      "type": "land",
      "location": "Bastos, Yaoundé",
      "city": "Yaoundé",
      "country": "Cameroon",
      "landSize": 2000,
      "description": "Terrain commercial de 2000m² situé dans le quartier huppé de Bastos. Idéal pour projets immobiliers d'envergure : centre commercial, immeuble de bureaux, résidence de luxe. Zone à forte valeur ajoutée, accès facile depuis les principaux axes.",
      "features": ["Zone commerciale", "Accès route goudronnée", "Raccordement eau", "Raccordement électricité", "Terrain plat", "Titre foncier", "Vue dégagée"],
      "images": [
        "https://images.unsplash.com/photo-1500382017468-9049fed747ef?w=800&q=80",
        "https://images.unsplash.com/photo-1444723121867-745f09db2088?w=800&q=80"
      ],
      "verified": false,
      "isNew": false,
      "isUrgent": true,
      "isFeatured": true,
      "agent": {
        "id": "a3",
        "name": "Claire Ngo",
        "agency": "Terres d'Afrique",
        "rating": 4.8,
        "listings": 27,
        "avatar": "https://images.unsplash.com/photo-1438761681033-6461ffad8d80?w=150&q=80",
        "phone": "+237 6 99 88 77 66",
        "email": "claire@terresafrique.com"
      },
      "createdAt": "2025-03-01T10:00:00Z"
    },
    {
      "id": "4",
      "title": "Modern Office Space in Brazzaville",
      "slug": "office-space-brazzaville",
      "price": 2500000,
      "priceUnit": "FCFA/month",
      "listingType": "rent",
      "type": "office",
      "location": "Plateau, Brazzaville",
      "city": "Brazzaville",
      "country": "Congo",
      "surface": 200,
      "description": "Bureaux modernes entièrement équipés au cœur du Plateau. Parfait pour start-ups, PME et entreprises établies. Espaces modulables, salles de réunion, fibre optique haut débit.",
      "features": ["Climatisation centrale", "Salle de réunion équipée", "Accès 24/7", "Parking sécurisé", "Fibre optique", "Cafétéria", "Espace de coworking"],
      "images": [
        "https://images.unsplash.com/photo-1497366754035-f200968a6e72?w=800&q=80",
        "https://images.unsplash.com/photo-1497215728101-856f4ea42174?w=800&q=80",
        "https://images.unsplash.com/photo-1486406146926-c627a92ad1ab?w=800&q=80"
      ],
      "verified": true,
      "isNew": false,
      "isUrgent": false,
      "isFeatured": true,
      "agent": {
        "id": "a4",
        "name": "Paul Mampouya",
        "agency": "Congo Immo Pro",
        "rating": 4.6,
        "listings": 31,
        "avatar": "https://images.unsplash.com/photo-1472099645785-5658abf4ff4e?w=150&q=80",
        "phone": "+242 06 123 4567",
        "email": "paul@congoimmo.com"
      },
      "createdAt": "2025-01-05T10:00:00Z"
    },
    {
      "id": "5",
      "title": "Beachfront Apartment in Port-Gentil",
      "slug": "beachfront-apartment-port-gentil",
      "price": 850000,
      "priceUnit": "FCFA/month",
      "listingType": "rent",
      "type": "apartment",
      "location": "Quartier Bord de Mer, Port-Gentil",
      "city": "Port-Gentil",
      "country": "Gabon",
      "rooms": 2,
      "bedrooms": 2,
      "bathrooms": 2,
      "surface": 85,
      "description": "Appartement avec vue imprenable sur l'océan. Accès direct à la plage. Cadre paradisiaque, idéal pour expatriés ou personnes souhaitant vivre au bord de l'eau. Finitions modernes, ambiance relaxante.",
      "features": ["Vue mer panoramique", "Plage privée", "Climatisation", "Parking privé", "Piscine commune", "Service de sécurité", "Accès plage"],
      "images": [
        "https://images.unsplash.com/photo-1512917774080-9991f1c4c750?w=800&q=80",
        "https://images.unsplash.com/photo-1448630360428-65456885c650?w=800&q=80",
        "https://images.unsplash.com/photo-1506485338023-6ce5f36692df?w=800&q=80"
      ],
      "verified": false,
      "isNew": true,
      "isUrgent": false,
      "isFeatured": true,
      "agent": {
        "id": "a5",
        "name": "Marie Lemba",
        "agency": "Gabon Beach Realty",
        "rating": 4.9,
        "listings": 19,
        "avatar": "https://images.unsplash.com/photo-1534528741775-53994a69daeb?w=150&q=80",
        "phone": "+241 66 123 456",
        "email": "marie@gabonbeach.com"
      },
      "createdAt": "2025-02-10T10:00:00Z"
    },
    {
      "id": "6",
      "title": "Family House in Yaoundé",
      "slug": "family-house-yaounde",
      "price": 120000000,
      "priceUnit": "FCFA",
      "listingType": "buy",
      "type": "house",
      "location": "Odza, Yaoundé",
      "city": "Yaoundé",
      "country": "Cameroon",
      "rooms": 4,
      "bedrooms": 4,
      "bathrooms": 3,
      "surface": 200,
      "landSize": 400,
      "description": "Maison familiale spacieuse dans le quartier calme d'Odza. Grand jardin de 400m², parfait pour les enfants. Espaces de vie lumineux, cuisine américaine, terrasse couverte. Proche des écoles et commodités.",
      "features": ["Jardin paysager", "Parking 2 places", "Terrasse couverte", "Cuisine américaine", "Buanderie", "Garde-manger", "Climatisation", "Puits"],
      "images": [
        "https://images.unsplash.com/photo-1564013799919-ab600027ffc6?w=800&q=80",
        "https://images.unsplash.com/photo-1568605114967-8130f3a36994?w=800&q=80",
        "https://images.unsplash.com/photo-1600585154526-990dced4db0d?w=800&q=80"
      ],
      "verified": false,
      "isNew": false,
      "isUrgent": false,
      "isFeatured": true,
      "agent": {
        "id": "a6",
        "name": "Éric Kamga",
        "agency": "Yaoundé Immo Plus",
        "rating": 4.4,
        "listings": 45,
        "avatar": "https://images.unsplash.com/photo-1500648767791-00dcc994a43e?w=150&q=80",
        "phone": "+237 6 55 44 33 22",
        "email": "eric@yaoundeimmo.com"
      },
      "createdAt": "2025-03-10T10:00:00Z"
    }
  ]
}